odoo/addons/pos_receipt_hide_price/README.rst
odoo/addons/pos_receipt_hide_price/__init__.py
odoo/addons/pos_receipt_hide_price/__manifest__.py
odoo/addons/pos_receipt_hide_price/i18n/pos_receipt_hide_price.pot
odoo/addons/pos_receipt_hide_price/readme/CONTRIBUTORS.rst
odoo/addons/pos_receipt_hide_price/readme/DESCRIPTION.rst
odoo/addons/pos_receipt_hide_price/readme/USAGE.rst
odoo/addons/pos_receipt_hide_price/static/description/icon.png
odoo/addons/pos_receipt_hide_price/static/description/index.html
odoo/addons/pos_receipt_hide_price/static/description/price-hidden.png
odoo/addons/pos_receipt_hide_price/static/description/price-shown.png
odoo/addons/pos_receipt_hide_price/static/src/js/OrderReceipt.js
odoo/addons/pos_receipt_hide_price/static/src/js/ReceiptScreen.js
odoo/addons/pos_receipt_hide_price/static/src/js/ReprintReceiptScreen.js
odoo/addons/pos_receipt_hide_price/static/src/xml/HidePrice.xml
odoo/addons/pos_receipt_hide_price/static/src/xml/OrderReceipt.xml
odoo/addons/pos_receipt_hide_price/static/src/xml/ReceiptScreen.xml
odoo/addons/pos_receipt_hide_price/static/src/xml/ReprintReceiptScreen.xml
odoo/addons/pos_receipt_hide_price/views/assets.xml
odoo14_addon_pos_receipt_hide_price-14.0.1.0.1.dist-info/METADATA
odoo14_addon_pos_receipt_hide_price-14.0.1.0.1.dist-info/WHEEL
odoo14_addon_pos_receipt_hide_price-14.0.1.0.1.dist-info/top_level.txt
odoo14_addon_pos_receipt_hide_price-14.0.1.0.1.dist-info/RECORD
